kanboard.py
kanboard-1.1.6.dist-info/LICENSE
kanboard-1.1.6.dist-info/METADATA
kanboard-1.1.6.dist-info/WHEEL
kanboard-1.1.6.dist-info/top_level.txt
kanboard-1.1.6.dist-info/RECORD
