Metadata-Version: 2.1
Name: kanboard
Version: 1.1.6
Summary: Client library for Kanboard
Author-email: Frédéric Guillot <fred@kanboard.net>
License: The MIT License (MIT)
Project-URL: Homepage, https://github.com/kanboard/python-api-client
Project-URL: Bug Reports, https://github.com/kanboard/python-api-client/issues
Project-URL: Source, https://github.com/kanboard/python-api-client
Keywords: kanboard,api,client
Classifier: Intended Audience :: Developers
Classifier: Intended Audience :: Information Technology
Classifier: License :: OSI Approved :: MIT License
Classifier: Programming Language :: Python
Classifier: Programming Language :: Python :: 3.7
Classifier: Programming Language :: Python :: 3.8
Classifier: Programming Language :: Python :: 3.9
Classifier: Programming Language :: Python :: 3.10
Classifier: Programming Language :: Python :: 3.11
Classifier: Programming Language :: Python :: 3.12
Classifier: Programming Language :: Python :: 3.13
Classifier: Programming Language :: Python :: 3 :: Only
Requires-Python: >=3.7
License-File: LICENSE
